StatisticalDiagrams/RobustStatistics.py
StatisticalDiagrams/StatisticalDiagrams.py
StatisticalDiagrams/__init__.py
StatisticalDiagrams/robust.py
StatisticalDiagrams-20.5.dist-info/COPYING
StatisticalDiagrams-20.5.dist-info/LICENSE.txt
StatisticalDiagrams-20.5.dist-info/METADATA
StatisticalDiagrams-20.5.dist-info/WHEEL
StatisticalDiagrams-20.5.dist-info/top_level.txt
StatisticalDiagrams-20.5.dist-info/RECORD
